tabledetector/__init__.py
tabledetector/bordered.py
tabledetector/consolidated.py
tabledetector/convertor.py
tabledetector/extractor.py
tabledetector/rotate.py
tabledetector/semibordered.py
tabledetector/tabledetector.py
tabledetector/unbordered.py
tabledetector-1.0.2.dist-info/LICENSE
tabledetector-1.0.2.dist-info/METADATA
tabledetector-1.0.2.dist-info/WHEEL
tabledetector-1.0.2.dist-info/top_level.txt
tabledetector-1.0.2.dist-info/RECORD
