Metadata-Version: 2.1
Name: tabledetector
Version: 1.0.2
Summary: End-to-End table structure detector
Home-page: https://github.com/rajban94/TableDetector
Download-URL: https://github.com/rajban94/TableDetector.git
Author: Rishav Banerjee
Author-email: rishavbanerjee10.rb@gmail.com
License: MIT License
Keywords: table detector
Classifier: Programming Language :: Python :: 3
Classifier: Development Status :: 1 - Planning
Classifier: Operating System :: OS Independent
License-File: LICENSE
Requires-Dist: opencv-python
Requires-Dist: numpy
Requires-Dist: Pillow
Requires-Dist: scipy
Requires-Dist: pdf2image
Requires-Dist: pandas
Requires-Dist: openpyxl
Requires-Dist: jinja2
Requires-Dist: easyocr
